cfgsrv/__init__.py
cfgsrv/composed.py
cfgsrv/core.py
cfgsrv/ini.py
cfgsrv/os.py
cfgsrv/yaml.py
cfg_service-0.1.3.dist-info/METADATA
cfg_service-0.1.3.dist-info/WHEEL
cfg_service-0.1.3.dist-info/RECORD
