Metadata-Version: 2.1
Name: cfg-service
Version: 0.1.3
Summary: Get all configuration parameters to deploy your application
License: LGPL
Author: Salvador Ruiz Romero
Author-email: sruiz@indoorclima.com
Requires-Python: >=3.11,<4.0
Classifier: License :: Other/Proprietary License
Classifier: Programming Language :: Python :: 3
Classifier: Programming Language :: Python :: 3.11
Requires-Dist: pyyaml (>=6.0,<7.0)
